lokalise_exporter/__init__.py
lokalise_exporter/json_utils.py
lokalise_exporter/kotlin_exporter.py
lokalise_exporter/main.py
lokalise_exporter/properties_utils.py
lokalise_exporter/strings_util.py
lokalise_exporter/xml_utils.py
iGenius_lokalise_exporter-0.22.dist-info/LICENSE
iGenius_lokalise_exporter-0.22.dist-info/METADATA
iGenius_lokalise_exporter-0.22.dist-info/WHEEL
iGenius_lokalise_exporter-0.22.dist-info/entry_points.txt
iGenius_lokalise_exporter-0.22.dist-info/top_level.txt
iGenius_lokalise_exporter-0.22.dist-info/RECORD
