Metadata-Version: 2.1
Name: iGenius-lokalise-exporter
Version: 0.22
Summary: Export strings from lokalise.com
Home-page: https://github.com/iGenius-Srl/lokalise-exporter
Author: iGenius
Author-email: code@igenius.net
License: Apache-2.0
Keywords: localization l10n internationalization i18n lokalise localise export exporter tools development
Platform: UNKNOWN
Classifier: Development Status :: 5 - Production/Stable
Classifier: Environment :: Console
Classifier: Intended Audience :: Developers
Classifier: License :: OSI Approved :: Apache Software License
Classifier: Operating System :: OS Independent
Classifier: Programming Language :: Python :: 2.7
Classifier: Programming Language :: Python :: 3
Classifier: Programming Language :: Python :: 3.0
Classifier: Programming Language :: Python :: 3.1
Classifier: Programming Language :: Python :: 3.2
Classifier: Programming Language :: Python :: 3.3
Classifier: Programming Language :: Python :: 3.4
Classifier: Programming Language :: Python :: 3.5
Classifier: Programming Language :: Python :: 3.6
Classifier: Programming Language :: Python :: 3.7
Classifier: Programming Language :: Python :: 3 :: Only
Classifier: Topic :: Software Development :: Internationalization
Classifier: Topic :: Software Development :: Localization
Requires-Python: >=2.7.9, <4
Requires-Dist: requests
Requires-Dist: begins
Requires-Dist: colorlog
Requires-Dist: xmltodict
Requires-Dist: future
Requires-Dist: chardet
Requires-Dist: backports.tempfile ; python_version < "3.2"
Requires-Dist: scandir ; python_version < "3.5"
